taoist/__init__.py
taoist/parent_project.py
taoist/parse_args.py
taoist/read_config.py
taoist/read_label_dict.py
taoist/read_project_dict.py
taoist/run_init.py
taoist/run_label.py
taoist/run_project.py
taoist/run_section.py
taoist/run_task.py
taoist/taoist_main.py
taoist-0.7.3.dist-info/LICENSE
taoist-0.7.3.dist-info/METADATA
taoist-0.7.3.dist-info/WHEEL
taoist-0.7.3.dist-info/entry_points.txt
taoist-0.7.3.dist-info/top_level.txt
taoist-0.7.3.dist-info/RECORD
