Metadata-Version: 2.1
Name: taoist
Version: 0.7.3
Summary: Python-based Terminal Utility for Todoist
Home-page: https://github.com/popgendad/taoist
Author: Daniel Garrigan
Author-email: Popgendad <popgendad@gmail.com>
License: MIT
Requires-Python: >=3.6
License-File: LICENSE
Requires-Dist: tabulate (>=0.8.9)
Requires-Dist: todoist-api-python (>=1.1.0)
Requires-Dist: termcolor (>=1.1.0)
